{
  "$schema": "https://developer.microsoft.com/json-schemas/fabric/item/report/definition/bookmark/2.1.0/schema.json",
  "displayName": "Customers Share",
  "name": "Bookmark917d224e78402879ca32",
  "options": {
    "targetVisualNames": [
      "b4546a2d82a492d071e2"
    ]
  },
  "explorationState": {
    "version": "1.3",
    "activeSection": "ReportSection3cf14a86d701727d0e8c",
    "sections": {
      "ReportSection3cf14a86d701727d0e8c": {
        "visualContainers": {
          "b4546a2d82a492d071e2": {
            "filters": {
              "byExpr": [
                {
                  "name": "32fbf1cc5be994288fb4",
                  "type": "Categorical",
                  "expression": {
                    "Column": {
                      "Expression": {
                        "SourceRef": {
                          "Entity": "dCustomer"
                        }
                      },
                      "Property": "CountryName"
                    }
                  },
                  "howCreated": 0
                },
                {
                  "name": "070becbdbd039ed1efe5",
                  "type": "Advanced",
                  "expression": {
                    "Column": {
                      "Expression": {
                        "SourceRef": {
                          "Entity": "dCustomer"
                        }
                      },
                      "Property": "CustomerKey"
                    }
                  },
                  "howCreated": 0
                },
                {
                  "name": "55f6cda46024461807e4",
                  "type": "Advanced",
                  "expression": {
                    "Measure": {
                      "Expression": {
                        "SourceRef": {
                          "Entity": "_Key Measures"
                        }
                      },
                      "Property": "Customers Average Sales on Country"
                    }
                  },
                  "howCreated": 0
                },
                {
                  "name": "e17fd16d5f989f559d73",
                  "type": "Advanced",
                  "expression": {
                    "Measure": {
                      "Expression": {
                        "SourceRef": {
                          "Entity": "_Key Measures"
                        }
                      },
                      "Property": "Gross Sales"
                    }
                  },
                  "howCreated": 0
                },
                {
                  "name": "b04274b376104641dfe4",
                  "type": "Categorical",
                  "expression": {
                    "Column": {
                      "Expression": {
                        "SourceRef": {
                          "Entity": "dCustomer"
                        }
                      },
                      "Property": "CityName"
                    }
                  },
                  "howCreated": 0
                },
                {
                  "name": "a8533f8abaefadff4cf7",
                  "type": "Categorical",
                  "expression": {
                    "Column": {
                      "Expression": {
                        "SourceRef": {
                          "Entity": "dCustomer"
                        }
                      },
                      "Property": "Customer"
                    }
                  },
                  "howCreated": 0
                },
                {
                  "name": "969135f8d58bac2787f4",
                  "type": "Advanced",
                  "expression": {
                    "Measure": {
                      "Expression": {
                        "SourceRef": {
                          "Entity": "_Key Measures"
                        }
                      },
                      "Property": "% Customers Share on Country"
                    }
                  },
                  "howCreated": 0
                },
                {
                  "name": "fc54e4894d34d466616d",
                  "type": "Categorical",
                  "expression": {
                    "Column": {
                      "Expression": {
                        "SourceRef": {
                          "Entity": "dCustomer"
                        }
                      },
                      "Property": "Region.1"
                    }
                  },
                  "howCreated": 0
                }
              ]
            },
            "singleVisual": {
              "visualType": "pivotTable",
              "objects": {},
              "orderBy": [
                {
                  "Direction": 2,
                  "Expression": {
                    "Measure": {
                      "Expression": {
                        "SourceRef": {
                          "Entity": "_Key Measures"
                        }
                      },
                      "Property": "Gross Sales"
                    }
                  }
                }
              ],
              "activeProjections": {
                "Rows": [
                  {
                    "Column": {
                      "Expression": {
                        "SourceRef": {
                          "Entity": "dCustomer"
                        }
                      },
                      "Property": "CountryName"
                    }
                  }
                ]
              },
              "expansionStates": [
                {
                  "roles": [
                    "Rows"
                  ],
                  "levels": [
                    {
                      "queryRefs": [
                        "dCustomer.CountryName"
                      ],
                      "isCollapsed": true,
                      "isPinned": true
                    },
                    {
                      "queryRefs": [
                        "dCustomer.CustomerKey"
                      ],
                      "isCollapsed": true,
                      "isPinned": true
                    }
                  ],
                  "root": {
                    "identityValues": null
                  }
                }
              ]
            }
          },
          "450825c2bd18547f0bd3": {
            "singleVisual": {
              "visualType": "actionButton",
              "objects": {}
            }
          },
          "b0fa3ee7a802d142f5ee": {
            "singleVisual": {
              "visualType": "actionButton",
              "objects": {}
            }
          },
          "7c880dca00905a49c84d": {
            "singleVisual": {
              "visualType": "basicShape",
              "objects": {}
            }
          },
          "0eaa2076ad12f2ac254d": {
            "singleVisual": {
              "visualType": "basicShape",
              "objects": {}
            }
          },
          "3677c3e270bca00287d5": {
            "singleVisual": {
              "visualType": "actionButton",
              "objects": {}
            }
          },
          "cb005eddead604c29aed": {
            "singleVisual": {
              "visualType": "textbox",
              "objects": {}
            }
          },
          "5901b81fdd7b8bb42d53": {
            "singleVisual": {
              "visualType": "basicShape",
              "objects": {}
            }
          },
          "1ecf4cb0b34fdf95336c": {
            "singleVisual": {
              "visualType": "basicShape",
              "objects": {}
            }
          },
          "4f1af665dc11f30e1a7e": {
            "singleVisual": {
              "visualType": "actionButton",
              "objects": {}
            }
          },
          "c77617e999178b4870c6": {
            "singleVisual": {
              "visualType": "actionButton",
              "objects": {}
            }
          },
          "c8c9f00352e9d6d202f7": {
            "singleVisual": {
              "visualType": "actionButton",
              "objects": {}
            }
          },
          "08560e5365f8aa9839ce": {
            "singleVisual": {
              "visualType": "basicShape",
              "objects": {}
            }
          },
          "5c3b92443ca52ff1f222": {
            "singleVisual": {
              "visualType": "actionButton",
              "objects": {}
            }
          },
          "e365bfa0d3ebddc7e408": {
            "singleVisual": {
              "visualType": "textbox",
              "objects": {}
            }
          },
          "932c91ba14a5bbdf3058": {
            "singleVisual": {
              "visualType": "actionButton",
              "objects": {}
            }
          },
          "40054461c36bd7ef490d": {
            "singleVisual": {
              "visualType": "actionButton",
              "objects": {}
            }
          },
          "37883bda86f7df8e6f70": {
            "singleVisual": {
              "visualType": "actionButton",
              "objects": {}
            }
          },
          "ffd619d0ba2c9e76a04a": {
            "singleVisual": {
              "visualType": "textbox",
              "objects": {}
            }
          },
          "ffedda4490993d213c4d": {
            "singleVisual": {
              "visualType": "actionButton",
              "objects": {}
            }
          },
          "a74b882231ed4c2fd3f0": {
            "singleVisual": {
              "visualType": "actionButton",
              "objects": {}
            }
          },
          "9085a55700e05d11f41a": {
            "singleVisual": {
              "visualType": "actionButton",
              "objects": {}
            }
          },
          "01714c6fd5f8005f4e37": {
            "singleVisual": {
              "visualType": "actionButton",
              "objects": {}
            }
          },
          "d67f02a8076c905dfb94": {
            "singleVisual": {
              "visualType": "textbox",
              "objects": {}
            }
          },
          "7edf18be59971ed985d8": {
            "singleVisual": {
              "visualType": "actionButton",
              "objects": {}
            }
          },
          "4395fc6ce806e2da0474": {
            "singleVisual": {
              "visualType": "actionButton",
              "objects": {}
            }
          },
          "bef8b0bdeaa8494e6619": {
            "singleVisual": {
              "visualType": "actionButton",
              "objects": {}
            }
          },
          "3418a0f5acfda9f5d02b": {
            "singleVisual": {
              "visualType": "basicShape",
              "objects": {}
            }
          },
          "d30d361d0a0b0c289d73": {
            "filters": {
              "byExpr": [
                {
                  "name": "7e493b29d8c81fdc80be",
                  "type": "Advanced",
                  "expression": {
                    "Column": {
                      "Expression": {
                        "SourceRef": {
                          "Entity": "dCalendar"
                        }
                      },
                      "Property": "Year"
                    }
                  },
                  "howCreated": 0
                }
              ]
            },
            "singleVisual": {
              "visualType": "slicer",
              "objects": {
                "merge": {
                  "general": [
                    {
                      "properties": {
                        "filter": {
                          "filter": {
                            "Version": 2,
                            "From": [
                              {
                                "Name": "d",
                                "Entity": "dCalendar",
                                "Type": 0
                              }
                            ],
                            "Where": [
                              {
                                "Condition": {
                                  "In": {
                                    "Expressions": [
                                      {
                                        "Column": {
                                          "Expression": {
                                            "SourceRef": {
                                              "Source": "d"
                                            }
                                          },
                                          "Property": "Year"
                                        }
                                      }
                                    ],
                                    "Values": [
                                      [
                                        {
                                          "Literal": {
                                            "Value": "2013L"
                                          }
                                        }
                                      ]
                                    ]
                                  }
                                }
                              }
                            ]
                          }
                        }
                      }
                    }
                  ],
                  "data": [
                    {
                      "properties": {
                        "mode": {
                          "expr": {
                            "Literal": {
                              "Value": "'Dropdown'"
                            }
                          }
                        }
                      }
                    }
                  ]
                }
              },
              "activeProjections": {
                "Values": [
                  {
                    "Column": {
                      "Expression": {
                        "SourceRef": {
                          "Entity": "dCalendar"
                        }
                      },
                      "Property": "Year"
                    }
                  }
                ]
              }
            }
          },
          "52cfcf4cd3e361f457cc": {
            "filters": {
              "byExpr": [
                {
                  "name": "a204dde875e6e7934225",
                  "type": "Categorical",
                  "expression": {
                    "Column": {
                      "Expression": {
                        "SourceRef": {
                          "Entity": "dCustomer"
                        }
                      },
                      "Property": "Region.1"
                    }
                  },
                  "howCreated": 0
                }
              ]
            },
            "singleVisual": {
              "visualType": "slicer",
              "objects": {
                "merge": {
                  "data": [
                    {
                      "properties": {
                        "mode": {
                          "expr": {
                            "Literal": {
                              "Value": "'Dropdown'"
                            }
                          }
                        }
                      }
                    }
                  ]
                }
              },
              "activeProjections": {
                "Values": [
                  {
                    "Column": {
                      "Expression": {
                        "SourceRef": {
                          "Entity": "dCustomer"
                        }
                      },
                      "Property": "Region.1"
                    }
                  }
                ]
              }
            }
          },
          "1d57f7a601104ab9af04": {
            "filters": {
              "byExpr": [
                {
                  "name": "0842b2d2a6c858ec06ff",
                  "type": "Advanced",
                  "expression": {
                    "Column": {
                      "Expression": {
                        "SourceRef": {
                          "Entity": "auxMore than"
                        }
                      },
                      "Property": "More than"
                    }
                  },
                  "howCreated": 0
                }
              ]
            },
            "singleVisual": {
              "visualType": "slicer",
              "objects": {
                "merge": {
                  "general": [
                    {
                      "properties": {
                        "filter": {
                          "filter": {
                            "Version": 2,
                            "From": [
                              {
                                "Name": "m",
                                "Entity": "auxMore than",
                                "Type": 0
                              }
                            ],
                            "Where": [
                              {
                                "Condition": {
                                  "Comparison": {
                                    "ComparisonKind": 0,
                                    "Left": {
                                      "Column": {
                                        "Expression": {
                                          "SourceRef": {
                                            "Source": "m"
                                          }
                                        },
                                        "Property": "More than"
                                      }
                                    },
                                    "Right": {
                                      "Literal": {
                                        "Value": "4.5D"
                                      }
                                    }
                                  }
                                }
                              }
                            ]
                          }
                        }
                      }
                    }
                  ],
                  "data": [
                    {
                      "properties": {
                        "numericStart": {
                          "expr": {
                            "Literal": {
                              "Value": "4.5D"
                            }
                          }
                        }
                      }
                    }
                  ]
                }
              },
              "activeProjections": {
                "Values": [
                  {
                    "Column": {
                      "Expression": {
                        "SourceRef": {
                          "Entity": "auxMore than"
                        }
                      },
                      "Property": "More than"
                    }
                  }
                ]
              }
            }
          },
          "acbc6428887a485540e3": {
            "filters": {
              "byExpr": [
                {
                  "name": "a0cfd133907bbe6ef3bc",
                  "type": "Advanced",
                  "expression": {
                    "Column": {
                      "Expression": {
                        "SourceRef": {
                          "Entity": "auxLess than"
                        }
                      },
                      "Property": "Less than"
                    }
                  },
                  "howCreated": 0
                }
              ]
            },
            "singleVisual": {
              "visualType": "slicer",
              "objects": {
                "merge": {
                  "general": [
                    {
                      "properties": {
                        "filter": {
                          "filter": {
                            "Version": 2,
                            "From": [
                              {
                                "Name": "l",
                                "Entity": "auxLess than",
                                "Type": 0
                              }
                            ],
                            "Where": [
                              {
                                "Condition": {
                                  "Comparison": {
                                    "ComparisonKind": 0,
                                    "Left": {
                                      "Column": {
                                        "Expression": {
                                          "SourceRef": {
                                            "Source": "l"
                                          }
                                        },
                                        "Property": "Less than"
                                      }
                                    },
                                    "Right": {
                                      "Literal": {
                                        "Value": "0D"
                                      }
                                    }
                                  }
                                }
                              }
                            ]
                          }
                        }
                      }
                    }
                  ],
                  "data": [
                    {
                      "properties": {
                        "numericStart": {
                          "expr": {
                            "Literal": {
                              "Value": "0D"
                            }
                          }
                        }
                      }
                    }
                  ]
                }
              },
              "activeProjections": {
                "Values": [
                  {
                    "Column": {
                      "Expression": {
                        "SourceRef": {
                          "Entity": "auxLess than"
                        }
                      },
                      "Property": "Less than"
                    }
                  }
                ]
              }
            }
          },
          "66d5d4a813bfb8228f22": {
            "singleVisual": {
              "visualType": "textbox",
              "objects": {}
            }
          }
        },
        "visualContainerGroups": {
          "d1e744c2b4b378106efd": {
            "isHidden": true
          }
        }
      }
    },
    "objects": {
      "merge": {
        "outspacePane": [
          {
            "properties": {
              "expanded": {
                "expr": {
                  "Literal": {
                    "Value": "false"
                  }
                }
              }
            }
          }
        ]
      }
    }
  }
}